[{"id":1,"name":"Rahul Kumar","age":30,"city":"Mumbai"},{"id":2,"name":"Priya Sharma","age":25,"city":"Delhi"},{"id":3,"name":"Aarav Singh","age":35,"city":"Bangalore"},{"id":4,"name":"Kavya Patel","age":40,"city":"Chennai"},{"id":5,"name":"Arjun Gupta","age":28,"city":"Kolkata"},{"id":6,"name":"Meera Joshi","age":32,"city":"Hyderabad"},{"id":7,"name":"Vikram Verma","age":45,"city":"Pune"},{"id":8,"name":"Sneha Tiwari","age":38,"city":"Ahmedabad"},{"id":9,"name":"Neha Reddy","age":27,"city":"Jaipur"},{"id":10,"name":"Rajesh Khanna","age":33,"city":"Lucknow"},{"id":1710425403127,"name":"Midhun","age":"25","city":"Chennai"},{"id":1715227099413,"name":"Mathi","age":"23","city":"Madurai"}]